pysocketftp/__init__.py
pysocketftp/socket.py
pysocketftp/socket_ftp_c/build/libsocket_ftp.so
pysocketftp_eba-0.0.1.dist-info/DESCRIPTION.rst
pysocketftp_eba-0.0.1.dist-info/METADATA
pysocketftp_eba-0.0.1.dist-info/RECORD
pysocketftp_eba-0.0.1.dist-info/WHEEL
pysocketftp_eba-0.0.1.dist-info/metadata.json
pysocketftp_eba-0.0.1.dist-info/top_level.txt
