Metadata-Version: 2.0
Name: pysocketftp-eba
Version: 0.0.1
Summary: Final projet to icog devtools course
Home-page: https://git.icog-labs.com/eba-alemayehu/Final-project
Author: Eba Alemayehu
Author-email: ebaalemayhu3@gmail.com
License: UNKNOWN
Platform: UNKNOWN
Classifier: Programming Language :: Python :: 2
Classifier: License :: OSI Approved :: MIT License
Classifier: Operating System :: OS Independent
Requires-Python: >=2.0
